README.md
setup.py
slackbot_ce/__init__.py
slackbot_ce/bot_id.py
slackbot_ce/slackpi.py
slackbot_ce/testit.py
slackbot_ce.egg-info/PKG-INFO
slackbot_ce.egg-info/SOURCES.txt
slackbot_ce.egg-info/dependency_links.txt
slackbot_ce.egg-info/top_level.txt
slackbot_ce/chris/__init__.py
slackbot_ce/chris/slacklib.py
slackbot_ce/code_em/__init__.py
slackbot_ce/code_em/aaruv/__init__.py
slackbot_ce/code_em/aaruv/slacklib.py
slackbot_ce/code_em/aidan/__init__.py
slackbot_ce/code_em/aidan/slacklib.py
slackbot_ce/code_em/al_kareem/__init__.py
slackbot_ce/code_em/al_kareem/slacklib.py
slackbot_ce/code_em/alec/__init__.py
slackbot_ce/code_em/alec/slacklib.py
slackbot_ce/code_em/alec_r/__init__.py
slackbot_ce/code_em/alec_r/slacklib.py
slackbot_ce/code_em/alex/__init__.py
slackbot_ce/code_em/alex/slacklib.py
slackbot_ce/code_em/alexander/__init__.py
slackbot_ce/code_em/alexander/slacklib.py
slackbot_ce/code_em/anaya/__init__.py
slackbot_ce/code_em/anaya/slacklib.py
slackbot_ce/code_em/anooshka/__init__.py
slackbot_ce/code_em/anooshka/slacklib.py
slackbot_ce/code_em/coy/__init__.py
slackbot_ce/code_em/coy/slacklib.py
slackbot_ce/code_em/evelyn/__init__.py
slackbot_ce/code_em/evelyn/slacklib.py
slackbot_ce/code_em/hadley/__init__.py
slackbot_ce/code_em/hadley/slacklib.py
slackbot_ce/code_em/lily/__init__.py
slackbot_ce/code_em/lily/slacklib.py
slackbot_ce/code_em/mattias/__init__.py
slackbot_ce/code_em/mattias/slacklib.py
slackbot_ce/code_em/owen/__init__.py
slackbot_ce/code_em/owen/slacklib.py
slackbot_ce/code_em/patrick/__init__.py
slackbot_ce/code_em/patrick/slacklib.py
slackbot_ce/code_em/qiuqiu/__init__.py
slackbot_ce/code_em/qiuqiu/slacklib.py
slackbot_ce/code_em/stephon/__init__.py
slackbot_ce/code_em/stephon/slacklib.py
slackbot_ce/code_em/summer/__init__.py
slackbot_ce/code_em/summer/slacklib.py
slackbot_ce/code_em/taixi/__init__.py
slackbot_ce/code_em/taixi/slacklib.py
slackbot_ce/code_em/travis/__init__.py
slackbot_ce/code_em/travis/slacklib.py
slackbot_ce/code_em/tyler/__init__.py
slackbot_ce/code_em/tyler/slacklib.py
slackbot_ce/code_em/zb/__init__.py
slackbot_ce/code_em/zb/slacklib.py
