Metadata-Version: 1.1
Name: slackbot-ce
Version: 0.2.522192348
Summary: Python Code for Tech Em Studios Create Em Class
Home-page: https://github.com/wray/code_em
Author: Techem Studios
Author-email: wray@techemstudios.com
License: UNKNOWN
Download-URL: https://github.com/wray/code_em/tarball/0.2.522192348
Keywords: slackbot,RPi,AWS
Platform: UNKNOWN
